MANIFEST.in
README.textile
setup.py
django_badbrowser/__init__.py
django_badbrowser/__init__.pyc
django_badbrowser/middleware.py
django_badbrowser/middleware.pyc
django_badbrowser/models.py
django_badbrowser/models.pyc
django_badbrowser/tests.py
django_badbrowser/urls.py
django_badbrowser/urls.pyc
django_badbrowser/views.py
django_badbrowser/views.pyc
django_badbrowser.egg-info/PKG-INFO
django_badbrowser.egg-info/SOURCES.txt
django_badbrowser.egg-info/dependency_links.txt
django_badbrowser.egg-info/requires.txt
django_badbrowser.egg-info/top_level.txt
django_badbrowser/static/django-badbrowser/background_browser.gif
django_badbrowser/static/django-badbrowser/browser_chrome.gif
django_badbrowser/static/django-badbrowser/browser_firefox.gif
django_badbrowser/static/django-badbrowser/browser_ie.gif
django_badbrowser/static/django-badbrowser/browser_opera.gif
django_badbrowser/static/django-badbrowser/browser_safari.gif
django_badbrowser/templates/django_badbrowser/base.html
django_badbrowser/templates/django_badbrowser/unsupported.html
django_badbrowser/uastrings/chrome6.0.458.1.txt
django_badbrowser/uastrings/ff1.0.txt
django_badbrowser/uastrings/ff3.1b3.txt
django_badbrowser/uastrings/ie6.1.txt
django_badbrowser/uastrings/ie6.txt
django_badbrowser/uastrings/ie7.txt
django_badbrowser/uastrings/ie7b.txt
django_badbrowser/uastrings/ie8.txt