Metadata-Version: 1.0
Name: django-badbrowser
Version: 1.0.7
Summary: Browser detection (including browser upgrade notices) for Django
Home-page: http://github.com/adamcharnock/django-badbrowser
Author: Adam Charnock
Author-email: adam@playnice.ly
License: MIT
Download-URL: git@github.com:adamcharnock/django-badbrowser.git
Platform: any
Classifier: Development Status :: 4 - Beta
Classifier: License :: OSI Approved :: MIT License
Classifier: Environment :: Web Environment
Classifier: Framework :: Django
Classifier: Intended Audience :: Developers
Classifier: Operating System :: OS Independent
Classifier: Programming Language :: Python
Classifier: Topic :: Software Development :: Libraries :: Application Frameworks
Classifier: Topic :: Software Development :: Libraries :: Python Modules
Classifier: Topic :: Internet :: WWW/HTTP :: Browsers
